setup.cfg
setup.py
cmq/__init__.py
cmq/account.py
cmq/cmq_client.py
cmq/cmq_exception.py
cmq/cmq_http.py
cmq/cmq_tool.py
cmq/queue.py
cmq/sign.py
cmq/subscription.py
cmq/topic.py
qcloud_cmq_sdk_py3.egg-info/PKG-INFO
qcloud_cmq_sdk_py3.egg-info/SOURCES.txt
qcloud_cmq_sdk_py3.egg-info/dependency_links.txt
qcloud_cmq_sdk_py3.egg-info/top_level.txt