Metadata-Version: 1.2
Name: qcloud-cmq-sdk-py3
Version: 0.1
Summary: Tencent Cloud SDK for CMQ API 2.0 running in python3
Home-page: https://github.com/tencentyun/cmq-python-sdk/tree/python3
Author: Tencent Cloud CMQ Team
Maintainer-email: yorkxyzhang@tencent.com
License: Apache License 2.0
Platform: any
Classifier: Development Status :: 5 - Production/Stable
Classifier: Intended Audience :: Developers
Classifier: License :: OSI Approved :: Apache Software License
Classifier: Programming Language :: Python
Classifier: Programming Language :: Python :: 3.6
